CHANGES.rst
LICENSE.rst
MANIFEST.in
README.rst
setup.cfg
setup.py
sphinx_graphml/__init__.py
sphinx_graphml/directives.py
sphinx_graphml/nodes.py
sphinx_graphml/version.py
sphinx_graphml.egg-info/PKG-INFO
sphinx_graphml.egg-info/SOURCES.txt
sphinx_graphml.egg-info/dependency_links.txt
sphinx_graphml.egg-info/not-zip-safe
sphinx_graphml.egg-info/requires.txt
sphinx_graphml.egg-info/top_level.txt
sphinx_graphml/static/js/GraphMLViewer.js
sphinx_graphml/static/js/GraphMLViewer.swf