Metadata-Version: 1.1
Name: sphinx-graphml
Version: 0.1b5
Summary: GraphML charts embedding extension for Sphinx
Home-page: https://bitbucket.org/tkhyn/sphinx-graphml/
Author: Thomas Khyn
Author-email: thomas@ksytek.com
License: UNKNOWN
Keywords: sphinx,graphml,yEd,chart
Platform: UNKNOWN
Classifier: Programming Language :: Python :: 3
Classifier: Development Status :: 4 - Beta
Classifier: License :: OSI Approved :: MIT License
Classifier: Environment :: Plugins
Classifier: Framework :: Sphinx :: Extension
Classifier: Intended Audience :: Developers
Classifier: Topic :: Software Development :: Documentation
Classifier: Topic :: Documentation :: Sphinx
